{
  "pills": [
    {
      "name": "reddymc redface",
      "id": "b593f1b8-8c3d-4f5e-a798-6e7a3569a85b",
      "temperature": 11.9375,
      "gravity": 1151.88,
      "battery": 56.0991
    },
    {
      "name": "yellow mc yellow face",
      "id": "176cc4c3-9e13-4106-b1c0-7455b4f9ca7c",
      "temperature": 18,
      "gravity": 1254.35,
      "battery": 59.3959
    }
  ],
  "lastUpdated": "2026-07-12T17:20:04.155578Z",
  "history": [
    {
      "reddy": {
        "temperature": 10.75,
        "gravity": 1152.52,
        "battery": 56.7165,
        "time": "2026-07-10T22:35:05.813565Z"
      },
      "yellow": {
        "temperature": 14.875,
        "gravity": 1022.12,
        "battery": 66.2398,
        "time": "2026-07-10T22:35:05.813565Z"
      }
    },
    {
      "reddy": {
        "temperature": 10.75,
        "gravity": 1152.52,
        "battery": 56.7165,
        "time": "2026-07-10T22:44:28.397504Z"
      },
      "yellow": {
        "temperature": 14.875,
        "gravity": 1022.12,
        "battery": 66.2398,
        "time": "2026-07-10T22:44:28.397504Z"
      }
    },
    {
      "reddy": {
        "temperature": 10.75,
        "gravity": 1153.53,
        "battery": 56.7459,
        "time": "2026-07-10T22:50:05.711156Z"
      },
      "yellow": {
        "temperature": 14.8125,
        "gravity": 1022.13,
        "battery": 66.1507,
        "time": "2026-07-10T22:50:05.711156Z"
      }
    },
    {
      "reddy": {
        "temperature": 10.75,
        "gravity": 1153.14,
        "battery": 56.7606,
        "time": "2026-07-10T23:05:04.346902Z"
      },
      "yellow": {
        "temperature": 14.8125,
        "gravity": 1022.21,
        "battery": 65.8165,
        "time": "2026-07-10T23:05:04.346902Z"
      }
    },
    {
      "reddy": {
        "temperature": 10.75,
        "gravity": 1153.83,
        "battery": 56.8536,
        "time": "2026-07-10T23:20:04.295797Z"
      },
      "yellow": {
        "temperature": 14.75,
        "gravity": 1022.11,
        "battery": 66.1878,
        "time": "2026-07-10T23:20:04.295797Z"
      }
    },
    {
      "reddy": {
        "temperature": 10.8125,
        "gravity": 1153.49,
        "battery": 56.643,
        "time": "2026-07-10T23:35:04.216039Z"
      },
      "yellow": {
        "temperature": 14.6875,
        "gravity": 1021.96,
        "battery": 66.2175,
        "time": "2026-07-10T23:35:04.216039Z"
      }
    },
    {
      "reddy": {
        "temperature": 10.8125,
        "gravity": 1153.49,
        "battery": 56.643,
        "time": "2026-07-10T23:42:51.389527Z"
      },
      "yellow": {
        "temperature": 14.6875,
        "gravity": 1021.96,
        "battery": 66.2175,
        "time": "2026-07-10T23:42:51.389527Z"
      }
    },
    {
      "reddy": {
        "temperature": 10.875,
        "gravity": 1152.59,
        "battery": 56.7532,
        "time": "2026-07-10T23:50:04.249711Z"
      },
      "yellow": {
        "temperature": 14.6875,
        "gravity": 1022.23,
        "battery": 66.1135,
        "time": "2026-07-10T23:50:04.249711Z"
      }
    },
    {
      "reddy": {
        "temperature": 11,
        "gravity": 1152.76,
        "battery": 56.6577,
        "time": "2026-07-11T00:05:07.140586Z"
      },
      "yellow": {
        "temperature": 14.625,
        "gravity": 1022.19,
        "battery": 66.2027,
        "time": "2026-07-11T00:05:07.140586Z"
      }
    },
    {
      "reddy": {
        "temperature": 11.0625,
        "gravity": 1153.13,
        "battery": 56.8046,
        "time": "2026-07-11T00:20:04.711554Z"
      },
      "yellow": {
        "temperature": 14.625,
        "gravity": 1022.12,
        "battery": 66.0987,
        "time": "2026-07-11T00:20:04.711554Z"
      }
    },
    {
      "reddy": {
        "temperature": 11.3125,
        "gravity": 1153.29,
        "battery": 56.8204,
        "time": "2026-07-11T00:35:03.348320Z"
      },
      "yellow": {
        "temperature": 14.5625,
        "gravity": 1022.11,
        "battery": 66.0838,
        "time": "2026-07-11T00:35:03.348320Z"
      }
    },
    {
      "reddy": {
        "temperature": 11.5,
        "gravity": 1152.38,
        "battery": 56.9281,
        "time": "2026-07-11T00:50:04.284465Z"
      },
      "yellow": {
        "temperature": 14.5625,
        "gravity": 1022.15,
        "battery": 66.1952,
        "time": "2026-07-11T00:50:04.284465Z"
      }
    },
    {
      "reddy": {
        "temperature": 11.8125,
        "gravity": 1152.62,
        "battery": 56.8287,
        "time": "2026-07-11T01:05:03.799480Z"
      },
      "yellow": {
        "temperature": 14.5625,
        "gravity": 1022.2,
        "battery": 66.0987,
        "time": "2026-07-11T01:05:03.799480Z"
      }
    },
    {
      "reddy": {
        "temperature": 11.8125,
        "gravity": 1152.62,
        "battery": 56.8287,
        "time": "2026-07-11T01:12:29.276574Z"
      },
      "yellow": {
        "temperature": 14.5625,
        "gravity": 1022.2,
        "battery": 66.0987,
        "time": "2026-07-11T01:12:29.276574Z"
      }
    },
    {
      "reddy": {
        "temperature": 12.25,
        "gravity": 1150.64,
        "battery": 56.7679,
        "time": "2026-07-11T01:20:03.774016Z"
      },
      "yellow": {
        "temperature": 14.5,
        "gravity": 1022.16,
        "battery": 65.9947,
        "time": "2026-07-11T01:20:03.774016Z"
      }
    },
    {
      "reddy": {
        "temperature": 13.3125,
        "gravity": 1151.33,
        "battery": 56.7091,
        "time": "2026-07-11T01:35:04.349526Z"
      },
      "yellow": {
        "temperature": 14.5,
        "gravity": 1022.11,
        "battery": 66.1878,
        "time": "2026-07-11T01:35:04.349526Z"
      }
    },
    {
      "reddy": {
        "temperature": 14.125,
        "gravity": 1150.64,
        "battery": 56.9861,
        "time": "2026-07-11T01:50:03.540329Z"
      },
      "yellow": {
        "temperature": 14.5,
        "gravity": 1022.31,
        "battery": 66.0764,
        "time": "2026-07-11T01:50:03.540329Z"
      }
    },
    {
      "reddy": {
        "temperature": 14.6875,
        "gravity": 1150.05,
        "battery": 57.0193,
        "time": "2026-07-11T02:05:04.329622Z"
      },
      "yellow": {
        "temperature": 14.5,
        "gravity": 1022.15,
        "battery": 65.8834,
        "time": "2026-07-11T02:05:04.329622Z"
      }
    },
    {
      "reddy": {
        "temperature": 17.25,
        "gravity": 1148.13,
        "battery": 56.8619,
        "time": "2026-07-11T02:20:03.007006Z"
      },
      "yellow": {
        "temperature": 14.5,
        "gravity": 1022.13,
        "battery": 66.0244,
        "time": "2026-07-11T02:20:03.007006Z"
      }
    },
    {
      "reddy": {
        "temperature": 18.3125,
        "gravity": 1146.83,
        "battery": 57.185,
        "time": "2026-07-11T02:35:05.217151Z"
      },
      "yellow": {
        "temperature": 14.4375,
        "gravity": 1022.2,
        "battery": 65.9799,
        "time": "2026-07-11T02:35:05.217151Z"
      }
    },
    {
      "reddy": {
        "temperature": 18.875,
        "gravity": 1146.98,
        "battery": 57.2347,
        "time": "2026-07-11T02:50:03.415936Z"
      },
      "yellow": {
        "temperature": 14.5,
        "gravity": 1022.19,
        "battery": 65.5789,
        "time": "2026-07-11T02:50:03.415936Z"
      }
    },
    {
      "reddy": {
        "temperature": 20.5625,
        "gravity": 1144.94,
        "battery": 57.3093,
        "time": "2026-07-11T03:05:04.405922Z"
      },
      "yellow": {
        "temperature": 14.5,
        "gravity": 1022.14,
        "battery": 65.9725,
        "time": "2026-07-11T03:05:04.405922Z"
      }
    },
    {
      "reddy": {
        "temperature": 21.0625,
        "gravity": 1144.73,
        "battery": 57.2679,
        "time": "2026-07-11T03:20:04.499023Z"
      },
      "yellow": {
        "temperature": 14.5,
        "gravity": 1022.27,
        "battery": 65.9873,
        "time": "2026-07-11T03:20:04.499023Z"
      }
    },
    {
      "reddy": {
        "temperature": 21.125,
        "gravity": 1144.62,
        "battery": 57.649,
        "time": "2026-07-11T03:35:04.587798Z"
      },
      "yellow": {
        "temperature": 14.5,
        "gravity": 1022.18,
        "battery": 66.017,
        "time": "2026-07-11T03:35:04.587798Z"
      }
    },
    {
      "reddy": {
        "temperature": 21.125,
        "gravity": 1145.09,
        "battery": 57.5164,
        "time": "2026-07-11T03:50:03.722210Z"
      },
      "yellow": {
        "temperature": 14.5,
        "gravity": 1022.24,
        "battery": 66.0616,
        "time": "2026-07-11T03:50:03.722210Z"
      }
    },
    {
      "reddy": {
        "temperature": 21.125,
        "gravity": 1144.72,
        "battery": 57.6076,
        "time": "2026-07-11T04:05:04.825627Z"
      },
      "yellow": {
        "temperature": 14.5,
        "gravity": 1022.14,
        "battery": 65.9799,
        "time": "2026-07-11T04:05:04.825627Z"
      }
    },
    {
      "reddy": {
        "temperature": 21.1875,
        "gravity": 1144.61,
        "battery": 57.6076,
        "time": "2026-07-11T04:20:10.432563Z"
      },
      "yellow": {
        "temperature": 14.5625,
        "gravity": 1022.32,
        "battery": 65.9131,
        "time": "2026-07-11T04:20:10.432563Z"
      }
    },
    {
      "reddy": {
        "temperature": 21.1875,
        "gravity": 1144.61,
        "battery": 57.6076,
        "time": "2026-07-11T04:31:49.817854Z"
      },
      "yellow": {
        "temperature": 14.5625,
        "gravity": 1022.32,
        "battery": 65.9131,
        "time": "2026-07-11T04:31:49.817854Z"
      }
    },
    {
      "reddy": {
        "temperature": 21.125,
        "gravity": 1144.47,
        "battery": 57.6573,
        "time": "2026-07-11T04:35:07.011248Z"
      },
      "yellow": {
        "temperature": 14.5625,
        "gravity": 1022.3,
        "battery": 65.8091,
        "time": "2026-07-11T04:35:07.011248Z"
      }
    },
    {
      "reddy": {
        "temperature": 21.875,
        "gravity": 1144.36,
        "battery": 57.3673,
        "time": "2026-07-11T04:50:03.416929Z"
      },
      "yellow": {
        "temperature": 14.5625,
        "gravity": 1022.16,
        "battery": 66.0096,
        "time": "2026-07-11T04:50:03.416929Z"
      }
    },
    {
      "reddy": {
        "temperature": 21.9375,
        "gravity": 1145.35,
        "battery": 57.5662,
        "time": "2026-07-11T05:05:04.140376Z"
      },
      "yellow": {
        "temperature": 14.5625,
        "gravity": 1022.16,
        "battery": 66.0096,
        "time": "2026-07-11T05:05:04.140376Z"
      }
    },
    {
      "reddy": {
        "temperature": 21.625,
        "gravity": 1143.9,
        "battery": 57.6159,
        "time": "2026-07-11T05:20:03.995669Z"
      },
      "yellow": {
        "temperature": 14.5625,
        "gravity": 1022.11,
        "battery": 66.0244,
        "time": "2026-07-11T05:20:03.995669Z"
      }
    },
    {
      "reddy": {
        "temperature": 21.5625,
        "gravity": 1143.78,
        "battery": 57.5827,
        "time": "2026-07-11T05:35:03.660336Z"
      },
      "yellow": {
        "temperature": 14.5625,
        "gravity": 1022.21,
        "battery": 66.0542,
        "time": "2026-07-11T05:35:03.660336Z"
      }
    },
    {
      "reddy": {
        "temperature": 21.375,
        "gravity": 1144.01,
        "battery": 57.4833,
        "time": "2026-07-11T05:50:03.350974Z"
      },
      "yellow": {
        "temperature": 14.5625,
        "gravity": 1022.19,
        "battery": 65.9725,
        "time": "2026-07-11T05:50:03.350974Z"
      }
    },
    {
      "reddy": {
        "temperature": 21.375,
        "gravity": 1144.01,
        "battery": 57.4833,
        "time": "2026-07-11T06:05:02.981242Z"
      },
      "yellow": {
        "temperature": 14.625,
        "gravity": 1022.33,
        "battery": 66.0318,
        "time": "2026-07-11T06:05:02.981242Z"
      }
    },
    {
      "reddy": {
        "temperature": 21.1875,
        "gravity": 1144.48,
        "battery": 57.4087,
        "time": "2026-07-11T06:20:04.307140Z"
      },
      "yellow": {
        "temperature": 14.625,
        "gravity": 1022.29,
        "battery": 66.0467,
        "time": "2026-07-11T06:20:04.307140Z"
      }
    },
    {
      "reddy": {
        "temperature": 21.125,
        "gravity": 1143.92,
        "battery": 57.5081,
        "time": "2026-07-11T06:35:04.197718Z"
      },
      "yellow": {
        "temperature": 14.625,
        "gravity": 1022.26,
        "battery": 65.8908,
        "time": "2026-07-11T06:35:04.197718Z"
      }
    },
    {
      "reddy": {
        "temperature": 20.9375,
        "gravity": 1144.56,
        "battery": 57.6407,
        "time": "2026-07-11T06:50:03.096279Z"
      },
      "yellow": {
        "temperature": 14.6875,
        "gravity": 1022.22,
        "battery": 65.7868,
        "time": "2026-07-11T06:50:03.096279Z"
      }
    },
    {
      "reddy": {
        "temperature": 20.75,
        "gravity": 1145.21,
        "battery": 57.5164,
        "time": "2026-07-11T06:59:52.738816Z"
      },
      "yellow": {
        "temperature": 14.6875,
        "gravity": 1022.26,
        "battery": 65.9725,
        "time": "2026-07-11T06:59:52.738816Z"
      }
    },
    {
      "reddy": {
        "temperature": 20.75,
        "gravity": 1145.21,
        "battery": 57.5164,
        "time": "2026-07-11T07:05:03.109368Z"
      },
      "yellow": {
        "temperature": 14.6875,
        "gravity": 1022.26,
        "battery": 65.9725,
        "time": "2026-07-11T07:05:03.109368Z"
      }
    },
    {
      "reddy": {
        "temperature": 20.5625,
        "gravity": 1144.89,
        "battery": 57.5662,
        "time": "2026-07-11T07:20:05.661999Z"
      },
      "yellow": {
        "temperature": 14.6875,
        "gravity": 1022.16,
        "battery": 65.9056,
        "time": "2026-07-11T07:20:05.661999Z"
      }
    },
    {
      "reddy": {
        "temperature": 20.3125,
        "gravity": 1144.68,
        "battery": 57.4916,
        "time": "2026-07-11T07:35:03.394319Z"
      },
      "yellow": {
        "temperature": 14.6875,
        "gravity": 1022.2,
        "battery": 65.9279,
        "time": "2026-07-11T07:35:03.394319Z"
      }
    },
    {
      "reddy": {
        "temperature": 21.5625,
        "gravity": 1143.73,
        "battery": 57.4502,
        "time": "2026-07-11T07:50:03.987895Z"
      },
      "yellow": {
        "temperature": 14.75,
        "gravity": 1022.21,
        "battery": 66.0318,
        "time": "2026-07-11T07:50:03.987895Z"
      }
    },
    {
      "reddy": {
        "temperature": 22.75,
        "gravity": 1142.56,
        "battery": 57.7816,
        "time": "2026-07-11T08:05:03.685964Z"
      },
      "yellow": {
        "temperature": 14.75,
        "gravity": 1022.21,
        "battery": 65.9353,
        "time": "2026-07-11T08:05:03.685964Z"
      }
    },
    {
      "reddy": {
        "temperature": 22.875,
        "gravity": 1143.12,
        "battery": 57.5827,
        "time": "2026-07-11T08:20:05.664318Z"
      },
      "yellow": {
        "temperature": 14.8125,
        "gravity": 1022.21,
        "battery": 66.0838,
        "time": "2026-07-11T08:20:05.664318Z"
      }
    },
    {
      "reddy": {
        "temperature": 22.25,
        "gravity": 1143.3,
        "battery": 57.6242,
        "time": "2026-07-11T08:35:03.544264Z"
      },
      "yellow": {
        "temperature": 14.8125,
        "gravity": 1022.1,
        "battery": 65.8908,
        "time": "2026-07-11T08:35:03.544264Z"
      }
    },
    {
      "reddy": {
        "temperature": 21.6875,
        "gravity": 1144.16,
        "battery": 57.1353,
        "time": "2026-07-11T08:50:03.424042Z"
      },
      "yellow": {
        "temperature": 14.8125,
        "gravity": 1022.24,
        "battery": 65.8834,
        "time": "2026-07-11T08:50:03.424042Z"
      }
    },
    {
      "reddy": {
        "temperature": 21.25,
        "gravity": 1144.51,
        "battery": 57.4419,
        "time": "2026-07-11T08:56:32.219463Z"
      },
      "yellow": {
        "temperature": 14.875,
        "gravity": 1022.14,
        "battery": 65.9131,
        "time": "2026-07-11T08:56:32.219463Z"
      }
    },
    {
      "reddy": {
        "temperature": 21.25,
        "gravity": 1144.51,
        "battery": 57.4419,
        "time": "2026-07-11T09:05:05.621274Z"
      },
      "yellow": {
        "temperature": 14.875,
        "gravity": 1022.14,
        "battery": 65.9131,
        "time": "2026-07-11T09:05:05.621274Z"
      }
    },
    {
      "reddy": {
        "temperature": 20.75,
        "gravity": 1145.56,
        "battery": 57.6159,
        "time": "2026-07-11T09:20:03.367359Z"
      },
      "yellow": {
        "temperature": 14.875,
        "gravity": 1022.04,
        "battery": 65.9502,
        "time": "2026-07-11T09:20:03.367359Z"
      }
    },
    {
      "reddy": {
        "temperature": 20.375,
        "gravity": 1144.48,
        "battery": 57.3839,
        "time": "2026-07-11T09:35:03.112530Z"
      },
      "yellow": {
        "temperature": 14.875,
        "gravity": 1022.29,
        "battery": 65.9353,
        "time": "2026-07-11T09:35:03.112530Z"
      }
    },
    {
      "reddy": {
        "temperature": 19.9375,
        "gravity": 1143.87,
        "battery": 57.4585,
        "time": "2026-07-11T09:50:04.780457Z"
      },
      "yellow": {
        "temperature": 14.9375,
        "gravity": 1022.15,
        "battery": 65.6903,
        "time": "2026-07-11T09:50:04.780457Z"
      }
    },
    {
      "reddy": {
        "temperature": 19.5625,
        "gravity": 1145.46,
        "battery": 57.2182,
        "time": "2026-07-11T10:05:03.189776Z"
      },
      "yellow": {
        "temperature": 14.9375,
        "gravity": 1022.17,
        "battery": 65.7794,
        "time": "2026-07-11T10:05:03.189776Z"
      }
    },
    {
      "reddy": {
        "temperature": 19.25,
        "gravity": 1145.41,
        "battery": 57.3093,
        "time": "2026-07-11T10:20:04.728133Z"
      },
      "yellow": {
        "temperature": 14.9375,
        "gravity": 1022.24,
        "battery": 66.0096,
        "time": "2026-07-11T10:20:04.728133Z"
      }
    },
    {
      "reddy": {
        "temperature": 18.875,
        "gravity": 1145.79,
        "battery": 57.1933,
        "time": "2026-07-11T10:21:59.930856Z"
      },
      "yellow": {
        "temperature": 14.9375,
        "gravity": 1022.17,
        "battery": 65.8908,
        "time": "2026-07-11T10:21:59.930856Z"
      }
    },
    {
      "reddy": {
        "temperature": 18.875,
        "gravity": 1145.79,
        "battery": 57.1933,
        "time": "2026-07-11T10:35:05.113765Z"
      },
      "yellow": {
        "temperature": 14.9375,
        "gravity": 1022.17,
        "battery": 65.8908,
        "time": "2026-07-11T10:35:05.113765Z"
      }
    },
    {
      "reddy": {
        "temperature": 18.625,
        "gravity": 1147.38,
        "battery": 57.0027,
        "time": "2026-07-11T10:50:04.981057Z"
      },
      "yellow": {
        "temperature": 15,
        "gravity": 1022.29,
        "battery": 65.8165,
        "time": "2026-07-11T10:50:04.981057Z"
      }
    },
    {
      "reddy": {
        "temperature": 18.375,
        "gravity": 1146.25,
        "battery": 57.1684,
        "time": "2026-07-11T11:05:03.322082Z"
      },
      "yellow": {
        "temperature": 15,
        "gravity": 1022.16,
        "battery": 65.8834,
        "time": "2026-07-11T11:05:03.322082Z"
      }
    },
    {
      "reddy": {
        "temperature": 18.0625,
        "gravity": 1147.06,
        "battery": 57.1104,
        "time": "2026-07-11T11:20:03.826786Z"
      },
      "yellow": {
        "temperature": 15,
        "gravity": 1022.06,
        "battery": 65.8685,
        "time": "2026-07-11T11:20:03.826786Z"
      }
    },
    {
      "reddy": {
        "temperature": 17.6875,
        "gravity": 1147.41,
        "battery": 57.1021,
        "time": "2026-07-11T11:32:20.724200Z"
      },
      "yellow": {
        "temperature": 15,
        "gravity": 1022.17,
        "battery": 65.9205,
        "time": "2026-07-11T11:32:20.724200Z"
      }
    },
    {
      "reddy": {
        "temperature": 17.6875,
        "gravity": 1147.41,
        "battery": 57.1021,
        "time": "2026-07-11T11:35:04.781646Z"
      },
      "yellow": {
        "temperature": 15,
        "gravity": 1022.17,
        "battery": 65.9205,
        "time": "2026-07-11T11:35:04.781646Z"
      }
    },
    {
      "reddy": {
        "temperature": 17.3125,
        "gravity": 1147.05,
        "battery": 56.9281,
        "time": "2026-07-11T11:50:03.540630Z"
      },
      "yellow": {
        "temperature": 15,
        "gravity": 1022.27,
        "battery": 65.8462,
        "time": "2026-07-11T11:50:03.540630Z"
      }
    },
    {
      "reddy": {
        "temperature": 16.9375,
        "gravity": 1147.79,
        "battery": 57.069,
        "time": "2026-07-11T12:05:04.930520Z"
      },
      "yellow": {
        "temperature": 15.0625,
        "gravity": 1022.28,
        "battery": 65.4695,
        "time": "2026-07-11T12:05:04.930520Z"
      }
    },
    {
      "reddy": {
        "temperature": 16.5625,
        "gravity": 1148.62,
        "battery": 57.0276,
        "time": "2026-07-11T12:20:03.411744Z"
      },
      "yellow": {
        "temperature": 15,
        "gravity": 1022.35,
        "battery": 65.7794,
        "time": "2026-07-11T12:20:03.411744Z"
      }
    },
    {
      "reddy": {
        "temperature": 16.125,
        "gravity": 1148.68,
        "battery": 57.0525,
        "time": "2026-07-11T12:35:04.889506Z"
      },
      "yellow": {
        "temperature": 15,
        "gravity": 1022.3,
        "battery": 65.8388,
        "time": "2026-07-11T12:35:04.889506Z"
      }
    },
    {
      "reddy": {
        "temperature": 15.8125,
        "gravity": 1147.8,
        "battery": 57.0193,
        "time": "2026-07-11T12:41:29.643806Z"
      },
      "yellow": {
        "temperature": 14.9375,
        "gravity": 1022.16,
        "battery": 65.8314,
        "time": "2026-07-11T12:41:29.643806Z"
      }
    },
    {
      "reddy": {
        "temperature": 15.8125,
        "gravity": 1147.8,
        "battery": 57.0193,
        "time": "2026-07-11T12:50:04.712430Z"
      },
      "yellow": {
        "temperature": 14.9375,
        "gravity": 1022.16,
        "battery": 65.8314,
        "time": "2026-07-11T12:50:04.712430Z"
      }
    },
    {
      "reddy": {
        "temperature": 15.5,
        "gravity": 1148.3,
        "battery": 56.9281,
        "time": "2026-07-11T13:05:03.541046Z"
      },
      "yellow": {
        "temperature": 14.9375,
        "gravity": 1022.27,
        "battery": 65.8314,
        "time": "2026-07-11T13:05:03.541046Z"
      }
    },
    {
      "reddy": {
        "temperature": 15.1875,
        "gravity": 1148.11,
        "battery": 57.0359,
        "time": "2026-07-11T13:20:06.550669Z"
      },
      "yellow": {
        "temperature": 14.9375,
        "gravity": 1022.15,
        "battery": 65.6755,
        "time": "2026-07-11T13:20:06.550669Z"
      }
    },
    {
      "reddy": {
        "temperature": 14.9375,
        "gravity": 1150.74,
        "battery": 56.9281,
        "time": "2026-07-11T13:35:03.191768Z"
      },
      "yellow": {
        "temperature": 14.9375,
        "gravity": 1022.04,
        "battery": 65.8611,
        "time": "2026-07-11T13:35:03.191768Z"
      }
    },
    {
      "reddy": {
        "temperature": 14.6875,
        "gravity": 1148.65,
        "battery": 56.8287,
        "time": "2026-07-11T13:50:04.846932Z"
      },
      "yellow": {
        "temperature": 14.9375,
        "gravity": 1022.19,
        "battery": 65.8314,
        "time": "2026-07-11T13:50:04.846932Z"
      }
    },
    {
      "reddy": {
        "temperature": 14.4375,
        "gravity": 1150.56,
        "battery": 56.9281,
        "time": "2026-07-11T14:05:03.551645Z"
      },
      "yellow": {
        "temperature": 14.9375,
        "gravity": 1022.16,
        "battery": 65.9353,
        "time": "2026-07-11T14:05:03.551645Z"
      }
    },
    {
      "reddy": {
        "temperature": 14.125,
        "gravity": 1149.82,
        "battery": 56.9779,
        "time": "2026-07-11T14:13:04.398180Z"
      },
      "yellow": {
        "temperature": 14.9375,
        "gravity": 1022.16,
        "battery": 65.8982,
        "time": "2026-07-11T14:13:04.398180Z"
      }
    },
    {
      "reddy": {
        "temperature": 14.125,
        "gravity": 1149.82,
        "battery": 56.9779,
        "time": "2026-07-11T14:20:03.015156Z"
      },
      "yellow": {
        "temperature": 14.9375,
        "gravity": 1022.16,
        "battery": 65.8982,
        "time": "2026-07-11T14:20:03.015156Z"
      }
    },
    {
      "reddy": {
        "temperature": 13.9375,
        "gravity": 1150.08,
        "battery": 56.8867,
        "time": "2026-07-11T14:35:09.462491Z"
      },
      "yellow": {
        "temperature": 14.875,
        "gravity": 1022.23,
        "battery": 65.7646,
        "time": "2026-07-11T14:35:09.462491Z"
      }
    },
    {
      "reddy": {
        "temperature": 13.75,
        "gravity": 1150.03,
        "battery": 56.8204,
        "time": "2026-07-11T14:50:04.961605Z"
      },
      "yellow": {
        "temperature": 14.875,
        "gravity": 1022.13,
        "battery": 65.6606,
        "time": "2026-07-11T14:50:04.961605Z"
      }
    },
    {
      "reddy": {
        "temperature": 13.5625,
        "gravity": 1150.04,
        "battery": 56.837,
        "time": "2026-07-11T15:05:04.434021Z"
      },
      "yellow": {
        "temperature": 14.875,
        "gravity": 1022.17,
        "battery": 65.9279,
        "time": "2026-07-11T15:05:04.434021Z"
      }
    },
    {
      "reddy": {
        "temperature": 13.3125,
        "gravity": 1150.3,
        "battery": 56.79,
        "time": "2026-07-11T15:20:05.414589Z"
      },
      "yellow": {
        "temperature": 14.875,
        "gravity": 1022.14,
        "battery": 65.6755,
        "time": "2026-07-11T15:20:05.414589Z"
      }
    },
    {
      "reddy": {
        "temperature": 13.125,
        "gravity": 1151,
        "battery": 56.7826,
        "time": "2026-07-11T15:26:00.269415Z"
      },
      "yellow": {
        "temperature": 14.8125,
        "gravity": 1022.21,
        "battery": 65.7868,
        "time": "2026-07-11T15:26:00.269415Z"
      }
    },
    {
      "reddy": {
        "temperature": 13.125,
        "gravity": 1151,
        "battery": 56.7826,
        "time": "2026-07-11T15:35:03.967556Z"
      },
      "yellow": {
        "temperature": 14.8125,
        "gravity": 1022.21,
        "battery": 65.7868,
        "time": "2026-07-11T15:35:03.967556Z"
      }
    },
    {
      "reddy": {
        "temperature": 12.9375,
        "gravity": 1152.26,
        "battery": 56.7312,
        "time": "2026-07-11T15:50:03.243074Z"
      },
      "yellow": {
        "temperature": 14.8125,
        "gravity": 1022.15,
        "battery": 65.8759,
        "time": "2026-07-11T15:50:03.243074Z"
      }
    },
    {
      "reddy": {
        "temperature": 12.8125,
        "gravity": 1150.48,
        "battery": 56.6797,
        "time": "2026-07-11T16:05:04.228521Z"
      },
      "yellow": {
        "temperature": 14.8125,
        "gravity": 1022.26,
        "battery": 65.5789,
        "time": "2026-07-11T16:05:04.228521Z"
      }
    },
    {
      "reddy": {
        "temperature": 12.625,
        "gravity": 1150.89,
        "battery": 56.7385,
        "time": "2026-07-11T16:20:04.267990Z"
      },
      "yellow": {
        "temperature": 14.75,
        "gravity": 1022.23,
        "battery": 65.8388,
        "time": "2026-07-11T16:20:04.267990Z"
      }
    },
    {
      "reddy": {
        "temperature": 12.4375,
        "gravity": 1150.19,
        "battery": 56.5401,
        "time": "2026-07-11T16:28:21.710549Z"
      },
      "yellow": {
        "temperature": 14.75,
        "gravity": 1022.23,
        "battery": 65.8388,
        "time": "2026-07-11T16:28:21.710549Z"
      }
    },
    {
      "reddy": {
        "temperature": 12.4375,
        "gravity": 1150.19,
        "battery": 56.5401,
        "time": "2026-07-11T16:35:07.505621Z"
      },
      "yellow": {
        "temperature": 14.75,
        "gravity": 1022.23,
        "battery": 65.8388,
        "time": "2026-07-11T16:35:07.505621Z"
      }
    },
    {
      "reddy": {
        "temperature": 12.3125,
        "gravity": 1152.38,
        "battery": 56.5621,
        "time": "2026-07-11T16:50:03.124967Z"
      },
      "yellow": {
        "temperature": 14.75,
        "gravity": 1022.14,
        "battery": 65.7794,
        "time": "2026-07-11T16:50:03.124967Z"
      }
    },
    {
      "reddy": {
        "temperature": 12.125,
        "gravity": 1151.37,
        "battery": 56.4372,
        "time": "2026-07-11T17:05:05.341313Z"
      },
      "yellow": {
        "temperature": 14.75,
        "gravity": 1022.2,
        "battery": 65.7646,
        "time": "2026-07-11T17:05:05.341313Z"
      }
    },
    {
      "reddy": {
        "temperature": 11.9375,
        "gravity": 1152.25,
        "battery": 56.5474,
        "time": "2026-07-11T17:20:04.859314Z"
      },
      "yellow": {
        "temperature": 14.6875,
        "gravity": 1022.17,
        "battery": 65.772,
        "time": "2026-07-11T17:20:04.859314Z"
      }
    },
    {
      "reddy": {
        "temperature": 11.8125,
        "gravity": 1151.99,
        "battery": 56.4886,
        "time": "2026-07-11T17:34:46.519823Z"
      },
      "yellow": {
        "temperature": 14.625,
        "gravity": 1022.23,
        "battery": 65.824,
        "time": "2026-07-11T17:34:46.519823Z"
      }
    },
    {
      "reddy": {
        "temperature": 11.8125,
        "gravity": 1151.99,
        "battery": 56.4886,
        "time": "2026-07-11T17:35:05.565927Z"
      },
      "yellow": {
        "temperature": 14.625,
        "gravity": 1022.23,
        "battery": 65.824,
        "time": "2026-07-11T17:35:05.565927Z"
      }
    },
    {
      "reddy": {
        "temperature": 11.625,
        "gravity": 1153.17,
        "battery": 56.2534,
        "time": "2026-07-11T17:50:03.436813Z"
      },
      "yellow": {
        "temperature": 14.625,
        "gravity": 1022.12,
        "battery": 65.7423,
        "time": "2026-07-11T17:50:03.436813Z"
      }
    },
    {
      "reddy": {
        "temperature": 11.5,
        "gravity": 1151.87,
        "battery": 56.5842,
        "time": "2026-07-11T18:05:04.475775Z"
      },
      "yellow": {
        "temperature": 14.5625,
        "gravity": 1022.48,
        "battery": 65.6383,
        "time": "2026-07-11T18:05:04.475775Z"
      }
    },
    {
      "reddy": {
        "temperature": 11.3125,
        "gravity": 1151.73,
        "battery": 56.518,
        "time": "2026-07-11T18:20:07.049646Z"
      },
      "yellow": {
        "temperature": 14.5625,
        "gravity": 1022.24,
        "battery": 65.7794,
        "time": "2026-07-11T18:20:07.049646Z"
      }
    },
    {
      "reddy": {
        "temperature": 11.1875,
        "gravity": 1153.12,
        "battery": 56.4151,
        "time": "2026-07-11T18:35:03.535414Z"
      },
      "yellow": {
        "temperature": 14.5,
        "gravity": 1022.22,
        "battery": 65.7497,
        "time": "2026-07-11T18:35:03.535414Z"
      }
    },
    {
      "reddy": {
        "temperature": 11.1875,
        "gravity": 1153.12,
        "battery": 56.4151,
        "time": "2026-07-11T18:37:59.202253Z"
      },
      "yellow": {
        "temperature": 14.5,
        "gravity": 1022.22,
        "battery": 65.7497,
        "time": "2026-07-11T18:37:59.202253Z"
      }
    },
    {
      "reddy": {
        "temperature": 11,
        "gravity": 1153.55,
        "battery": 56.3931,
        "time": "2026-07-11T18:50:03.887603Z"
      },
      "yellow": {
        "temperature": 14.4375,
        "gravity": 1022.12,
        "battery": 65.8017,
        "time": "2026-07-11T18:50:03.887603Z"
      }
    },
    {
      "reddy": {
        "temperature": 10.875,
        "gravity": 1152.95,
        "battery": 56.3857,
        "time": "2026-07-11T19:05:05.747753Z"
      },
      "yellow": {
        "temperature": 14.4375,
        "gravity": 1022.22,
        "battery": 65.8017,
        "time": "2026-07-11T19:05:05.747753Z"
      }
    },
    {
      "reddy": {
        "temperature": 10.75,
        "gravity": 1152.76,
        "battery": 56.2902,
        "time": "2026-07-11T19:20:03.253209Z"
      },
      "yellow": {
        "temperature": 14.375,
        "gravity": 1022.2,
        "battery": 65.7571,
        "time": "2026-07-11T19:20:03.253209Z"
      }
    },
    {
      "reddy": {
        "temperature": 10.625,
        "gravity": 1152.48,
        "battery": 56.2975,
        "time": "2026-07-11T19:35:04.076540Z"
      },
      "yellow": {
        "temperature": 14.375,
        "gravity": 1022.25,
        "battery": 65.6532,
        "time": "2026-07-11T19:35:04.076540Z"
      }
    },
    {
      "reddy": {
        "temperature": 10.5,
        "gravity": 1153.39,
        "battery": 56.224,
        "time": "2026-07-11T19:50:03.972704Z"
      },
      "yellow": {
        "temperature": 14.3125,
        "gravity": 1022.25,
        "battery": 65.7794,
        "time": "2026-07-11T19:50:03.972704Z"
      }
    },
    {
      "reddy": {
        "temperature": 10.375,
        "gravity": 1152.01,
        "battery": 56.2314,
        "time": "2026-07-11T19:54:07.976350Z"
      },
      "yellow": {
        "temperature": 14.25,
        "gravity": 1022.24,
        "battery": 65.7274,
        "time": "2026-07-11T19:54:07.976350Z"
      }
    },
    {
      "reddy": {
        "temperature": 10.375,
        "gravity": 1152.01,
        "battery": 56.2314,
        "time": "2026-07-11T20:05:03.950271Z"
      },
      "yellow": {
        "temperature": 14.25,
        "gravity": 1022.24,
        "battery": 65.7274,
        "time": "2026-07-11T20:05:03.950271Z"
      }
    },
    {
      "reddy": {
        "temperature": 10.25,
        "gravity": 1152.76,
        "battery": 56.0255,
        "time": "2026-07-11T20:20:05.062788Z"
      },
      "yellow": {
        "temperature": 14.25,
        "gravity": 1022.19,
        "battery": 65.7497,
        "time": "2026-07-11T20:20:05.062788Z"
      }
    },
    {
      "reddy": {
        "temperature": 10.1875,
        "gravity": 1152.38,
        "battery": 56.2534,
        "time": "2026-07-11T20:35:04.639838Z"
      },
      "yellow": {
        "temperature": 14.125,
        "gravity": 1022.22,
        "battery": 65.8462,
        "time": "2026-07-11T20:35:04.639838Z"
      }
    },
    {
      "reddy": {
        "temperature": 10.0625,
        "gravity": 1152.58,
        "battery": 56.2167,
        "time": "2026-07-11T20:50:03.815117Z"
      },
      "yellow": {
        "temperature": 14.0625,
        "gravity": 1022.36,
        "battery": 65.7646,
        "time": "2026-07-11T20:50:03.815117Z"
      }
    },
    {
      "reddy": {
        "temperature": 9.9375,
        "gravity": 1153.87,
        "battery": 56.1946,
        "time": "2026-07-11T20:59:39.137942Z"
      },
      "yellow": {
        "temperature": 14.0625,
        "gravity": 1022.09,
        "battery": 65.8314,
        "time": "2026-07-11T20:59:39.137942Z"
      }
    },
    {
      "reddy": {
        "temperature": 9.9375,
        "gravity": 1153.87,
        "battery": 56.1946,
        "time": "2026-07-11T21:05:03.977755Z"
      },
      "yellow": {
        "temperature": 14.0625,
        "gravity": 1022.09,
        "battery": 65.8314,
        "time": "2026-07-11T21:05:03.977755Z"
      }
    },
    {
      "reddy": {
        "temperature": 9.875,
        "gravity": 1152.54,
        "battery": 56.1652,
        "time": "2026-07-11T21:20:05.669580Z"
      },
      "yellow": {
        "temperature": 14,
        "gravity": 1022.17,
        "battery": 65.6977,
        "time": "2026-07-11T21:20:05.669580Z"
      }
    },
    {
      "reddy": {
        "temperature": 9.8125,
        "gravity": 1154.48,
        "battery": 56.1505,
        "time": "2026-07-11T21:35:03.271099Z"
      },
      "yellow": {
        "temperature": 13.9375,
        "gravity": 1022.17,
        "battery": 65.7646,
        "time": "2026-07-11T21:35:03.271099Z"
      }
    },
    {
      "reddy": {
        "temperature": 9.8125,
        "gravity": 1152.72,
        "battery": 56.1652,
        "time": "2026-07-11T21:50:03.817568Z"
      },
      "yellow": {
        "temperature": 13.875,
        "gravity": 1022.22,
        "battery": 65.7349,
        "time": "2026-07-11T21:50:03.817568Z"
      }
    },
    {
      "reddy": {
        "temperature": 9.8125,
        "gravity": 1153.33,
        "battery": 56.1579,
        "time": "2026-07-11T22:00:58.021296Z"
      },
      "yellow": {
        "temperature": 13.8125,
        "gravity": 1022.29,
        "battery": 65.6532,
        "time": "2026-07-11T22:00:58.021296Z"
      }
    },
    {
      "reddy": {
        "temperature": 9.8125,
        "gravity": 1153.33,
        "battery": 56.1579,
        "time": "2026-07-11T22:05:04.677342Z"
      },
      "yellow": {
        "temperature": 13.8125,
        "gravity": 1022.29,
        "battery": 65.6532,
        "time": "2026-07-11T22:05:04.677342Z"
      }
    },
    {
      "reddy": {
        "temperature": 9.875,
        "gravity": 1154.31,
        "battery": 56.1946,
        "time": "2026-07-11T22:20:04.754914Z"
      },
      "yellow": {
        "temperature": 13.8125,
        "gravity": 1022.3,
        "battery": 65.7868,
        "time": "2026-07-11T22:20:04.754914Z"
      }
    },
    {
      "reddy": {
        "temperature": 9.9375,
        "gravity": 1153.88,
        "battery": 56.0697,
        "time": "2026-07-11T22:35:10.092463Z"
      },
      "yellow": {
        "temperature": 13.75,
        "gravity": 1022.17,
        "battery": 65.6086,
        "time": "2026-07-11T22:35:10.092463Z"
      }
    },
    {
      "reddy": {
        "temperature": 10,
        "gravity": 1154.1,
        "battery": 56.1505,
        "time": "2026-07-11T22:50:05.183518Z"
      },
      "yellow": {
        "temperature": 13.6875,
        "gravity": 1022.3,
        "battery": 65.6383,
        "time": "2026-07-11T22:50:05.183518Z"
      }
    },
    {
      "reddy": {
        "temperature": 10.125,
        "gravity": 1153.59,
        "battery": 56.202,
        "time": "2026-07-11T23:05:03.748088Z"
      },
      "yellow": {
        "temperature": 13.6875,
        "gravity": 1022.21,
        "battery": 65.7571,
        "time": "2026-07-11T23:05:03.748088Z"
      }
    },
    {
      "reddy": {
        "temperature": 10.1875,
        "gravity": 1152.42,
        "battery": 56.0844,
        "time": "2026-07-11T23:12:03.933377Z"
      },
      "yellow": {
        "temperature": 13.625,
        "gravity": 1022.18,
        "battery": 65.5566,
        "time": "2026-07-11T23:12:03.933377Z"
      }
    },
    {
      "reddy": {
        "temperature": 10.1875,
        "gravity": 1152.42,
        "battery": 56.0844,
        "time": "2026-07-11T23:20:03.579900Z"
      },
      "yellow": {
        "temperature": 13.625,
        "gravity": 1022.18,
        "battery": 65.5566,
        "time": "2026-07-11T23:20:03.579900Z"
      }
    },
    {
      "reddy": {
        "temperature": 10.3125,
        "gravity": 1152.19,
        "battery": 55.8712,
        "time": "2026-07-11T23:35:05.489736Z"
      },
      "yellow": {
        "temperature": 13.625,
        "gravity": 1022.36,
        "battery": 65.6606,
        "time": "2026-07-11T23:35:05.489736Z"
      }
    },
    {
      "reddy": {
        "temperature": 10.375,
        "gravity": 1152.49,
        "battery": 56.1431,
        "time": "2026-07-11T23:50:04.632497Z"
      },
      "yellow": {
        "temperature": 13.5625,
        "gravity": 1022.32,
        "battery": 65.5566,
        "time": "2026-07-11T23:50:04.632497Z"
      }
    },
    {
      "reddy": {
        "temperature": 10.375,
        "gravity": 1154.33,
        "battery": 55.9815,
        "time": "2026-07-12T00:05:04.680086Z"
      },
      "yellow": {
        "temperature": 13.5625,
        "gravity": 1022.27,
        "battery": 65.7052,
        "time": "2026-07-12T00:05:04.680086Z"
      }
    },
    {
      "reddy": {
        "temperature": 10.4375,
        "gravity": 1152.46,
        "battery": 56.1138,
        "time": "2026-07-12T00:13:16.521045Z"
      },
      "yellow": {
        "temperature": 13.5,
        "gravity": 1022.22,
        "battery": 65.8462,
        "time": "2026-07-12T00:13:16.521045Z"
      }
    },
    {
      "reddy": {
        "temperature": 10.4375,
        "gravity": 1152.46,
        "battery": 56.1138,
        "time": "2026-07-12T00:20:05.424053Z"
      },
      "yellow": {
        "temperature": 13.5,
        "gravity": 1022.22,
        "battery": 65.8462,
        "time": "2026-07-12T00:20:05.424053Z"
      }
    },
    {
      "reddy": {
        "temperature": 10.5625,
        "gravity": 1152.71,
        "battery": 56.0991,
        "time": "2026-07-12T00:35:04.826519Z"
      },
      "yellow": {
        "temperature": 13.5,
        "gravity": 1022.25,
        "battery": 65.6977,
        "time": "2026-07-12T00:35:04.826519Z"
      }
    },
    {
      "reddy": {
        "temperature": 10.75,
        "gravity": 1151.94,
        "battery": 56.1064,
        "time": "2026-07-12T00:50:05.489431Z"
      },
      "yellow": {
        "temperature": 13.4375,
        "gravity": 1022.25,
        "battery": 65.7052,
        "time": "2026-07-12T00:50:05.489431Z"
      }
    },
    {
      "reddy": {
        "temperature": 11.125,
        "gravity": 1152.61,
        "battery": 56.0991,
        "time": "2026-07-12T01:05:03.780910Z"
      },
      "yellow": {
        "temperature": 13.4375,
        "gravity": 1022.22,
        "battery": 65.7868,
        "time": "2026-07-12T01:05:03.780910Z"
      }
    },
    {
      "reddy": {
        "temperature": 11.5,
        "gravity": 1151.89,
        "battery": 56.2461,
        "time": "2026-07-12T01:20:03.703922Z"
      },
      "yellow": {
        "temperature": 13.8125,
        "gravity": 1022.29,
        "battery": 65.5566,
        "time": "2026-07-12T01:20:03.703922Z"
      }
    },
    {
      "reddy": {
        "temperature": 11.8125,
        "gravity": 1151.76,
        "battery": 56.0476,
        "time": "2026-07-12T01:35:05.028516Z"
      },
      "yellow": {
        "temperature": 14.125,
        "gravity": 1153.4,
        "battery": 65.1961,
        "time": "2026-07-12T01:35:05.028516Z"
      }
    },
    {
      "reddy": {
        "temperature": 12.1875,
        "gravity": 1151.45,
        "battery": 56.2975,
        "time": "2026-07-12T01:50:03.273521Z"
      },
      "yellow": {
        "temperature": 14.1875,
        "gravity": 1153.28,
        "battery": 65.0966,
        "time": "2026-07-12T01:50:03.273521Z"
      }
    },
    {
      "reddy": {
        "temperature": 13.625,
        "gravity": 1149.86,
        "battery": 56.2387,
        "time": "2026-07-12T02:05:03.625870Z"
      },
      "yellow": {
        "temperature": 14,
        "gravity": 1314.97,
        "battery": 63.7294,
        "time": "2026-07-12T02:05:03.625870Z"
      }
    },
    {
      "reddy": {
        "temperature": 14.0625,
        "gravity": 1150.06,
        "battery": 56.5768,
        "time": "2026-07-12T02:20:10.458809Z"
      },
      "yellow": {
        "temperature": 14,
        "gravity": 1311.69,
        "battery": 63.8703,
        "time": "2026-07-12T02:20:10.458809Z"
      }
    },
    {
      "reddy": {
        "temperature": 14.875,
        "gravity": 1148.47,
        "battery": 56.4592,
        "time": "2026-07-12T02:35:03.049180Z"
      },
      "yellow": {
        "temperature": 14,
        "gravity": 1311.69,
        "battery": 63.8703,
        "time": "2026-07-12T02:35:03.049180Z"
      }
    },
    {
      "reddy": {
        "temperature": 15.125,
        "gravity": 1149.16,
        "battery": 56.2755,
        "time": "2026-07-12T02:50:03.928869Z"
      },
      "yellow": {
        "temperature": 14,
        "gravity": 1311.69,
        "battery": 63.8703,
        "time": "2026-07-12T02:50:03.928869Z"
      }
    },
    {
      "reddy": {
        "temperature": 15.625,
        "gravity": 1149.54,
        "battery": 56.6283,
        "time": "2026-07-12T03:05:03.961851Z"
      },
      "yellow": {
        "temperature": 14,
        "gravity": 1311.69,
        "battery": 63.8703,
        "time": "2026-07-12T03:05:03.961851Z"
      }
    },
    {
      "reddy": {
        "temperature": 16.5,
        "gravity": 1147.53,
        "battery": 56.6356,
        "time": "2026-07-12T03:20:03.123196Z"
      },
      "yellow": {
        "temperature": 14.4375,
        "gravity": 1310.85,
        "battery": 64.1188,
        "time": "2026-07-12T03:20:03.123196Z"
      }
    },
    {
      "reddy": {
        "temperature": 16.875,
        "gravity": 1146.73,
        "battery": 56.7018,
        "time": "2026-07-12T03:35:05.541251Z"
      },
      "yellow": {
        "temperature": 15.4375,
        "gravity": 1305.23,
        "battery": 63.5388,
        "time": "2026-07-12T03:35:05.541251Z"
      }
    },
    {
      "reddy": {
        "temperature": 17.4375,
        "gravity": 1146.32,
        "battery": 56.8701,
        "time": "2026-07-12T03:50:07.268867Z"
      },
      "yellow": {
        "temperature": 15.875,
        "gravity": 1304.2,
        "battery": 63.5223,
        "time": "2026-07-12T03:50:07.268867Z"
      }
    },
    {
      "reddy": {
        "temperature": 18.0625,
        "gravity": 1147.27,
        "battery": 56.8453,
        "time": "2026-07-12T04:02:55.000668Z"
      },
      "yellow": {
        "temperature": 16,
        "gravity": 1303.22,
        "battery": 63.4228,
        "time": "2026-07-12T04:02:55.000668Z"
      }
    },
    {
      "reddy": {
        "temperature": 18.0625,
        "gravity": 1147.27,
        "battery": 56.8453,
        "time": "2026-07-12T04:05:05.691072Z"
      },
      "yellow": {
        "temperature": 16,
        "gravity": 1303.22,
        "battery": 63.4228,
        "time": "2026-07-12T04:05:05.691072Z"
      }
    },
    {
      "reddy": {
        "temperature": 18.9375,
        "gravity": 1145.56,
        "battery": 56.8701,
        "time": "2026-07-12T04:20:04.132036Z"
      },
      "yellow": {
        "temperature": 15.6875,
        "gravity": 1304.24,
        "battery": 63.4974,
        "time": "2026-07-12T04:20:04.132036Z"
      }
    },
    {
      "reddy": {
        "temperature": 19.5625,
        "gravity": 1144.33,
        "battery": 56.9447,
        "time": "2026-07-12T04:35:03.129797Z"
      },
      "yellow": {
        "temperature": 15.5625,
        "gravity": 1302.7,
        "battery": 63.5223,
        "time": "2026-07-12T04:35:03.129797Z"
      }
    },
    {
      "reddy": {
        "temperature": 20.5625,
        "gravity": 1145.52,
        "battery": 56.9696,
        "time": "2026-07-12T04:50:05.741376Z"
      },
      "yellow": {
        "temperature": 15.5625,
        "gravity": 1302.7,
        "battery": 63.5223,
        "time": "2026-07-12T04:50:05.741376Z"
      }
    },
    {
      "reddy": {
        "temperature": 21.875,
        "gravity": 1144.14,
        "battery": 57.0856,
        "time": "2026-07-12T05:05:04.113991Z"
      },
      "yellow": {
        "temperature": 15.5625,
        "gravity": 1302.7,
        "battery": 63.5223,
        "time": "2026-07-12T05:05:04.113991Z"
      }
    },
    {
      "reddy": {
        "temperature": 21.6875,
        "gravity": 1143.33,
        "battery": 56.9281,
        "time": "2026-07-12T05:20:03.788053Z"
      },
      "yellow": {
        "temperature": 15.875,
        "gravity": 1302.82,
        "battery": 63.4808,
        "time": "2026-07-12T05:20:03.788053Z"
      }
    },
    {
      "reddy": {
        "temperature": 21.625,
        "gravity": 1144.02,
        "battery": 57.0939,
        "time": "2026-07-12T05:35:04.170340Z"
      },
      "yellow": {
        "temperature": 17.4375,
        "gravity": 1262.45,
        "battery": 63.05,
        "time": "2026-07-12T05:35:04.170340Z"
      }
    },
    {
      "reddy": {
        "temperature": 21.875,
        "gravity": 1143.46,
        "battery": 57.0607,
        "time": "2026-07-12T05:50:05.644300Z"
      },
      "yellow": {
        "temperature": 17.75,
        "gravity": 1258.27,
        "battery": 63.4063,
        "time": "2026-07-12T05:50:05.644300Z"
      }
    },
    {
      "reddy": {
        "temperature": 22.25,
        "gravity": 1144.11,
        "battery": 56.9281,
        "time": "2026-07-12T06:05:04.812693Z"
      },
      "yellow": {
        "temperature": 17.375,
        "gravity": 1260.11,
        "battery": 63.514,
        "time": "2026-07-12T06:05:04.812693Z"
      }
    },
    {
      "reddy": {
        "temperature": 22.125,
        "gravity": 1144.39,
        "battery": 57.127,
        "time": "2026-07-12T06:20:03.709865Z"
      },
      "yellow": {
        "temperature": 17.875,
        "gravity": 1256.61,
        "battery": 63.2405,
        "time": "2026-07-12T06:20:03.709865Z"
      }
    },
    {
      "reddy": {
        "temperature": 21.875,
        "gravity": 1143.24,
        "battery": 57.1436,
        "time": "2026-07-12T06:35:04.123071Z"
      },
      "yellow": {
        "temperature": 17.6875,
        "gravity": 1259.1,
        "battery": 63.4477,
        "time": "2026-07-12T06:35:04.123071Z"
      }
    },
    {
      "reddy": {
        "temperature": 21.625,
        "gravity": 1144.09,
        "battery": 57.2182,
        "time": "2026-07-12T06:47:10.719492Z"
      },
      "yellow": {
        "temperature": 17.625,
        "gravity": 1257.54,
        "battery": 63.514,
        "time": "2026-07-12T06:47:10.719492Z"
      }
    },
    {
      "reddy": {
        "temperature": 21.625,
        "gravity": 1144.09,
        "battery": 57.2182,
        "time": "2026-07-12T06:50:04.628603Z"
      },
      "yellow": {
        "temperature": 17.625,
        "gravity": 1257.54,
        "battery": 63.514,
        "time": "2026-07-12T06:50:04.628603Z"
      }
    },
    {
      "reddy": {
        "temperature": 21.4375,
        "gravity": 1143.72,
        "battery": 56.9696,
        "time": "2026-07-12T07:05:04.807256Z"
      },
      "yellow": {
        "temperature": 17.5,
        "gravity": 1258.38,
        "battery": 63.4228,
        "time": "2026-07-12T07:05:04.807256Z"
      }
    },
    {
      "reddy": {
        "temperature": 21.25,
        "gravity": 1145.13,
        "battery": 56.837,
        "time": "2026-07-12T07:20:04.419753Z"
      },
      "yellow": {
        "temperature": 18.125,
        "gravity": 1256.22,
        "battery": 63.2986,
        "time": "2026-07-12T07:20:04.419753Z"
      }
    },
    {
      "reddy": {
        "temperature": 21,
        "gravity": 1144.32,
        "battery": 57.0607,
        "time": "2026-07-12T07:35:04.812829Z"
      },
      "yellow": {
        "temperature": 18.125,
        "gravity": 1256.22,
        "battery": 63.2986,
        "time": "2026-07-12T07:35:04.812829Z"
      }
    },
    {
      "reddy": {
        "temperature": 20.9375,
        "gravity": 1144.28,
        "battery": 56.9944,
        "time": "2026-07-12T07:50:11.212068Z"
      },
      "yellow": {
        "temperature": 18.125,
        "gravity": 1256.22,
        "battery": 63.2986,
        "time": "2026-07-12T07:50:11.212068Z"
      }
    },
    {
      "reddy": {
        "temperature": 21,
        "gravity": 1142.67,
        "battery": 56.9779,
        "time": "2026-07-12T08:05:04.551615Z"
      },
      "yellow": {
        "temperature": 18.125,
        "gravity": 1256.22,
        "battery": 63.2986,
        "time": "2026-07-12T08:05:04.551615Z"
      }
    },
    {
      "reddy": {
        "temperature": 20.75,
        "gravity": 1145.41,
        "battery": 57.0525,
        "time": "2026-07-12T08:20:03.016601Z"
      },
      "yellow": {
        "temperature": 18.125,
        "gravity": 1256.22,
        "battery": 63.2986,
        "time": "2026-07-12T08:20:03.016601Z"
      }
    },
    {
      "reddy": {
        "temperature": 20.5,
        "gravity": 1145.25,
        "battery": 56.9033,
        "time": "2026-07-12T08:35:04.307623Z"
      },
      "yellow": {
        "temperature": 18.125,
        "gravity": 1256.22,
        "battery": 63.2986,
        "time": "2026-07-12T08:35:04.307623Z"
      }
    },
    {
      "reddy": {
        "temperature": 20.25,
        "gravity": 1144.55,
        "battery": 57.0193,
        "time": "2026-07-12T08:50:05.172475Z"
      },
      "yellow": {
        "temperature": 18.125,
        "gravity": 1256.22,
        "battery": 63.2986,
        "time": "2026-07-12T08:50:05.172475Z"
      }
    },
    {
      "reddy": {
        "temperature": 19.875,
        "gravity": 1144.27,
        "battery": 57.0525,
        "time": "2026-07-12T09:05:04.215871Z"
      },
      "yellow": {
        "temperature": 18.125,
        "gravity": 1256.22,
        "battery": 63.2986,
        "time": "2026-07-12T09:05:04.215871Z"
      }
    },
    {
      "reddy": {
        "temperature": 19.875,
        "gravity": 1144.27,
        "battery": 57.0525,
        "time": "2026-07-12T09:08:35.453532Z"
      },
      "yellow": {
        "temperature": 18.125,
        "gravity": 1256.22,
        "battery": 63.2986,
        "time": "2026-07-12T09:08:35.453532Z"
      }
    },
    {
      "reddy": {
        "temperature": 19.5625,
        "gravity": 1145.37,
        "battery": 56.9199,
        "time": "2026-07-12T09:20:03.789261Z"
      },
      "yellow": {
        "temperature": 18.125,
        "gravity": 1256.22,
        "battery": 63.2986,
        "time": "2026-07-12T09:20:03.789261Z"
      }
    },
    {
      "reddy": {
        "temperature": 19.1875,
        "gravity": 1145.21,
        "battery": 56.8287,
        "time": "2026-07-12T09:35:04.607731Z"
      },
      "yellow": {
        "temperature": 18.125,
        "gravity": 1256.22,
        "battery": 63.2986,
        "time": "2026-07-12T09:35:04.607731Z"
      }
    },
    {
      "reddy": {
        "temperature": 18.8125,
        "gravity": 1145.15,
        "battery": 56.8287,
        "time": "2026-07-12T09:50:04.163257Z"
      },
      "yellow": {
        "temperature": 18.125,
        "gravity": 1256.22,
        "battery": 63.2986,
        "time": "2026-07-12T09:50:04.163257Z"
      }
    },
    {
      "reddy": {
        "temperature": 18.4375,
        "gravity": 1145.71,
        "battery": 56.9199,
        "time": "2026-07-12T10:05:03.641977Z"
      },
      "yellow": {
        "temperature": 18.125,
        "gravity": 1256.22,
        "battery": 63.2986,
        "time": "2026-07-12T10:05:03.641977Z"
      }
    },
    {
      "reddy": {
        "temperature": 18,
        "gravity": 1147,
        "battery": 56.8453,
        "time": "2026-07-12T10:20:03.093754Z"
      },
      "yellow": {
        "temperature": 18.125,
        "gravity": 1256.22,
        "battery": 63.2986,
        "time": "2026-07-12T10:20:03.093754Z"
      }
    },
    {
      "reddy": {
        "temperature": 17.6875,
        "gravity": 1147.03,
        "battery": 56.895,
        "time": "2026-07-12T10:35:04.706969Z"
      },
      "yellow": {
        "temperature": 18.0625,
        "gravity": 1240.87,
        "battery": 58.9153,
        "time": "2026-07-12T10:35:04.706969Z"
      }
    },
    {
      "reddy": {
        "temperature": 17.3125,
        "gravity": 1147.46,
        "battery": 56.7459,
        "time": "2026-07-12T10:44:20.446852Z"
      },
      "yellow": {
        "temperature": 18,
        "gravity": 1254.35,
        "battery": 59.3959,
        "time": "2026-07-12T10:44:20.446852Z"
      }
    },
    {
      "reddy": {
        "temperature": 17.3125,
        "gravity": 1147.46,
        "battery": 56.7459,
        "time": "2026-07-12T10:50:04.902638Z"
      },
      "yellow": {
        "temperature": 18,
        "gravity": 1254.35,
        "battery": 59.3959,
        "time": "2026-07-12T10:50:04.902638Z"
      }
    },
    {
      "reddy": {
        "temperature": 17,
        "gravity": 1147.78,
        "battery": 56.7165,
        "time": "2026-07-12T11:05:09.194942Z"
      },
      "yellow": {
        "temperature": 18,
        "gravity": 1254.35,
        "battery": 59.3959,
        "time": "2026-07-12T11:05:09.194942Z"
      }
    },
    {
      "reddy": {
        "temperature": 16.75,
        "gravity": 1147.96,
        "battery": 56.7973,
        "time": "2026-07-12T11:20:03.659690Z"
      },
      "yellow": {
        "temperature": 18,
        "gravity": 1254.35,
        "battery": 59.3959,
        "time": "2026-07-12T11:20:03.659690Z"
      }
    },
    {
      "reddy": {
        "temperature": 16.5,
        "gravity": 1147.67,
        "battery": 56.6577,
        "time": "2026-07-12T11:35:03.452611Z"
      },
      "yellow": {
        "temperature": 18,
        "gravity": 1254.35,
        "battery": 59.3959,
        "time": "2026-07-12T11:35:03.452611Z"
      }
    },
    {
      "reddy": {
        "temperature": 16.3125,
        "gravity": 1147.4,
        "battery": 56.5915,
        "time": "2026-07-12T11:47:21.235974Z"
      },
      "yellow": {
        "temperature": 18,
        "gravity": 1254.35,
        "battery": 59.3959,
        "time": "2026-07-12T11:47:21.235974Z"
      }
    },
    {
      "reddy": {
        "temperature": 16.3125,
        "gravity": 1147.4,
        "battery": 56.5915,
        "time": "2026-07-12T11:50:04.946976Z"
      },
      "yellow": {
        "temperature": 18,
        "gravity": 1254.35,
        "battery": 59.3959,
        "time": "2026-07-12T11:50:04.946976Z"
      }
    },
    {
      "reddy": {
        "temperature": 16.0625,
        "gravity": 1147.83,
        "battery": 56.5915,
        "time": "2026-07-12T12:05:03.108451Z"
      },
      "yellow": {
        "temperature": 18,
        "gravity": 1254.35,
        "battery": 59.3959,
        "time": "2026-07-12T12:05:03.108451Z"
      }
    },
    {
      "reddy": {
        "temperature": 15.8125,
        "gravity": 1148.07,
        "battery": 56.6136,
        "time": "2026-07-12T12:20:19.279240Z"
      },
      "yellow": {
        "temperature": 18,
        "gravity": 1254.35,
        "battery": 59.3959,
        "time": "2026-07-12T12:20:19.279240Z"
      }
    },
    {
      "reddy": {
        "temperature": 15.5625,
        "gravity": 1147.77,
        "battery": 56.3343,
        "time": "2026-07-12T12:35:03.326120Z"
      },
      "yellow": {
        "temperature": 18,
        "gravity": 1254.35,
        "battery": 59.3959,
        "time": "2026-07-12T12:35:03.326120Z"
      }
    },
    {
      "reddy": {
        "temperature": 15.375,
        "gravity": 1148.67,
        "battery": 56.2755,
        "time": "2026-07-12T12:50:04.546342Z"
      },
      "yellow": {
        "temperature": 18,
        "gravity": 1254.35,
        "battery": 59.3959,
        "time": "2026-07-12T12:50:04.546342Z"
      }
    },
    {
      "reddy": {
        "temperature": 15.125,
        "gravity": 1148.99,
        "battery": 56.5474,
        "time": "2026-07-12T13:05:03.638222Z"
      },
      "yellow": {
        "temperature": 18,
        "gravity": 1254.35,
        "battery": 59.3959,
        "time": "2026-07-12T13:05:03.638222Z"
      }
    },
    {
      "reddy": {
        "temperature": 14.9375,
        "gravity": 1149.89,
        "battery": 56.3563,
        "time": "2026-07-12T13:20:03.165404Z"
      },
      "yellow": {
        "temperature": 18,
        "gravity": 1254.35,
        "battery": 59.3959,
        "time": "2026-07-12T13:20:03.165404Z"
      }
    },
    {
      "reddy": {
        "temperature": 14.6875,
        "gravity": 1149.41,
        "battery": 56.349,
        "time": "2026-07-12T13:35:05.113607Z"
      },
      "yellow": {
        "temperature": 18,
        "gravity": 1254.35,
        "battery": 59.3959,
        "time": "2026-07-12T13:35:05.113607Z"
      }
    },
    {
      "reddy": {
        "temperature": 14.5,
        "gravity": 1150.73,
        "battery": 56.3637,
        "time": "2026-07-12T13:44:35.256565Z"
      },
      "yellow": {
        "temperature": 18,
        "gravity": 1254.35,
        "battery": 59.3959,
        "time": "2026-07-12T13:44:35.256565Z"
      }
    },
    {
      "reddy": {
        "temperature": 14.5,
        "gravity": 1150.73,
        "battery": 56.3637,
        "time": "2026-07-12T13:50:03.760418Z"
      },
      "yellow": {
        "temperature": 18,
        "gravity": 1254.35,
        "battery": 59.3959,
        "time": "2026-07-12T13:50:03.760418Z"
      }
    },
    {
      "reddy": {
        "temperature": 14.25,
        "gravity": 1149.68,
        "battery": 56.4225,
        "time": "2026-07-12T14:05:05.025032Z"
      },
      "yellow": {
        "temperature": 18,
        "gravity": 1254.35,
        "battery": 59.3959,
        "time": "2026-07-12T14:05:05.025032Z"
      }
    },
    {
      "reddy": {
        "temperature": 14.0625,
        "gravity": 1149.18,
        "battery": 56.1873,
        "time": "2026-07-12T14:20:03.419923Z"
      },
      "yellow": {
        "temperature": 18,
        "gravity": 1254.35,
        "battery": 59.3959,
        "time": "2026-07-12T14:20:03.419923Z"
      }
    },
    {
      "reddy": {
        "temperature": 13.875,
        "gravity": 1149.03,
        "battery": 56.1431,
        "time": "2026-07-12T14:35:03.439289Z"
      },
      "yellow": {
        "temperature": 18,
        "gravity": 1254.35,
        "battery": 59.3959,
        "time": "2026-07-12T14:35:03.439289Z"
      }
    },
    {
      "reddy": {
        "temperature": 13.875,
        "gravity": 1149.03,
        "battery": 56.1431,
        "time": "2026-07-12T14:44:10.018952Z"
      },
      "yellow": {
        "temperature": 18,
        "gravity": 1254.35,
        "battery": 59.3959,
        "time": "2026-07-12T14:44:10.018952Z"
      }
    },
    {
      "reddy": {
        "temperature": 13.6875,
        "gravity": 1150.7,
        "battery": 56.2387,
        "time": "2026-07-12T14:50:13.254491Z"
      },
      "yellow": {
        "temperature": 18,
        "gravity": 1254.35,
        "battery": 59.3959,
        "time": "2026-07-12T14:50:13.254491Z"
      }
    },
    {
      "reddy": {
        "temperature": 13.5,
        "gravity": 1150.38,
        "battery": 56.2314,
        "time": "2026-07-12T15:05:04.294346Z"
      },
      "yellow": {
        "temperature": 18,
        "gravity": 1254.35,
        "battery": 59.3959,
        "time": "2026-07-12T15:05:04.294346Z"
      }
    },
    {
      "reddy": {
        "temperature": 13.3125,
        "gravity": 1149.99,
        "battery": 56.1285,
        "time": "2026-07-12T15:20:04.058449Z"
      },
      "yellow": {
        "temperature": 18,
        "gravity": 1254.35,
        "battery": 59.3959,
        "time": "2026-07-12T15:20:04.058449Z"
      }
    },
    {
      "reddy": {
        "temperature": 13.125,
        "gravity": 1150.97,
        "battery": 56.1431,
        "time": "2026-07-12T15:35:05.252443Z"
      },
      "yellow": {
        "temperature": 18,
        "gravity": 1254.35,
        "battery": 59.3959,
        "time": "2026-07-12T15:35:05.252443Z"
      }
    },
    {
      "reddy": {
        "temperature": 13.125,
        "gravity": 1150.97,
        "battery": 56.1431,
        "time": "2026-07-12T15:43:42.997742Z"
      },
      "yellow": {
        "temperature": 18,
        "gravity": 1254.35,
        "battery": 59.3959,
        "time": "2026-07-12T15:43:42.997742Z"
      }
    },
    {
      "reddy": {
        "temperature": 12.9375,
        "gravity": 1150.59,
        "battery": 56.1652,
        "time": "2026-07-12T15:50:04.079645Z"
      },
      "yellow": {
        "temperature": 18,
        "gravity": 1254.35,
        "battery": 59.3959,
        "time": "2026-07-12T15:50:04.079645Z"
      }
    },
    {
      "reddy": {
        "temperature": 12.75,
        "gravity": 1151.31,
        "battery": 55.9594,
        "time": "2026-07-12T16:05:04.919159Z"
      },
      "yellow": {
        "temperature": 18,
        "gravity": 1254.35,
        "battery": 59.3959,
        "time": "2026-07-12T16:05:04.919159Z"
      }
    },
    {
      "reddy": {
        "temperature": 12.5625,
        "gravity": 1150.96,
        "battery": 56.0255,
        "time": "2026-07-12T16:20:04.876821Z"
      },
      "yellow": {
        "temperature": 18,
        "gravity": 1254.35,
        "battery": 59.3959,
        "time": "2026-07-12T16:20:04.876821Z"
      }
    },
    {
      "reddy": {
        "temperature": 12.375,
        "gravity": 1151.46,
        "battery": 55.8712,
        "time": "2026-07-12T16:35:03.805349Z"
      },
      "yellow": {
        "temperature": 18,
        "gravity": 1254.35,
        "battery": 59.3959,
        "time": "2026-07-12T16:35:03.805349Z"
      }
    },
    {
      "reddy": {
        "temperature": 12.375,
        "gravity": 1151.46,
        "battery": 55.8712,
        "time": "2026-07-12T16:39:29.103584Z"
      },
      "yellow": {
        "temperature": 18,
        "gravity": 1254.35,
        "battery": 59.3959,
        "time": "2026-07-12T16:39:29.103584Z"
      }
    },
    {
      "reddy": {
        "temperature": 12.25,
        "gravity": 1151.29,
        "battery": 56.055,
        "time": "2026-07-12T16:50:03.138222Z"
      },
      "yellow": {
        "temperature": 18,
        "gravity": 1254.35,
        "battery": 59.3959,
        "time": "2026-07-12T16:50:03.138222Z"
      }
    },
    {
      "reddy": {
        "temperature": 12.125,
        "gravity": 1151.2,
        "battery": 56.0623,
        "time": "2026-07-12T17:05:03.489870Z"
      },
      "yellow": {
        "temperature": 18,
        "gravity": 1254.35,
        "battery": 59.3959,
        "time": "2026-07-12T17:05:03.489870Z"
      }
    },
    {
      "reddy": {
        "temperature": 11.9375,
        "gravity": 1151.88,
        "battery": 56.0991,
        "time": "2026-07-12T17:20:04.155578Z"
      },
      "yellow": {
        "temperature": 18,
        "gravity": 1254.35,
        "battery": 59.3959,
        "time": "2026-07-12T17:20:04.155578Z"
      }
    }
  ]
}